github_stats_pages/__init__.py
github_stats_pages/gts_run.py
github_stats_pages/logger.py
github_stats_pages/repo_list.py
github_stats_pages/stats_plots.py
github_stats_pages/templates/about.html
github_stats_pages/templates/index.html
github_stats_pages/templates/page.html
github_stats_pages/templates/repositories.html
github_stats_pages/templates/styles/css/style.css
github_stats_pages/templates/styles/img/bokeh-logo-grey.svg
github_stats_pages/templates/styles/img/bootstrap-logo-grey.svg
github_stats_pages/templates/styles/img/pandas-logo-grey.svg
github_stats_pages/templates/styles/img/python-logo-generic.svg
github_stats_pages/templates/styles/img/shields-logo.svg
github_stats_pages/templates/styles/js/bootstrap.min.js
github_stats_pages/templates/styles/js/jquery.min.js
github_stats_pages/templates/styles/js/main.js
github_stats_pages/templates/styles/js/popper.js
github_stats_pages-0.4.14.data/scripts/get_repo_list
github_stats_pages-0.4.14.data/scripts/gts_run_all_repos
github_stats_pages-0.4.14.data/scripts/make_stats_plots
github_stats_pages-0.4.14.data/scripts/merge_csv
github_stats_pages-0.4.14.dist-info/LICENSE
github_stats_pages-0.4.14.dist-info/METADATA
github_stats_pages-0.4.14.dist-info/WHEEL
github_stats_pages-0.4.14.dist-info/top_level.txt
github_stats_pages-0.4.14.dist-info/RECORD
