Metadata-Version: 2.1
Name: github-stats-pages
Version: 0.4.14
Summary: "Retrieve statistics for a user's repositories and populate the information onto a GitHub static page"
Home-page: https://github.com/astrochun/github-stats-pages
Author: Chun Ly
Author-email: astro.chun@gmail.com
Maintainer: Chun Ly
Maintainer-email: astro.chun@gmail.com
License: MIT
Project-URL: Tracker, https://github.com/astrochun/github-stats-pages/issues
Project-URL: Source, https://github.com/astrochun/github-stats-pages
Project-URL: Documentation, https://github.com/astrochun/github-stats-pages/blob/main/README.md
Classifier: Development Status :: 4 - Beta
Classifier: Programming Language :: Python :: 3 :: Only
Classifier: Programming Language :: Python :: 3.7
Classifier: Programming Language :: Python :: 3.8
Classifier: Programming Language :: Python :: 3.9
Requires-Python: >=3.7
License-File: LICENSE
Requires-Dist: requests (>=2.22.0)
Requires-Dist: pandas (==1.2.4)
Requires-Dist: github-traffic-stats (==1.2.0)
Requires-Dist: Jinja2 (==3.0.3)
Requires-Dist: bokeh (==2.3.0)
Requires-Dist: markdown (==3.3.4)
Requires-Dist: PyGithub (==1.55)
Requires-Dist: tabulate (==0.8.7)
Requires-Dist: rich (<13.0.0,>=12.4.1)
Provides-Extra: test
Requires-Dist: pytest (<8.0.0,>=7.1.2) ; extra == 'test'
Requires-Dist: pytest-cov (<4.0.0,>=3.0.0) ; extra == 'test'
